werkpool/__init__.py
werkpool-0.2.0.dist-info/METADATA
werkpool-0.2.0.dist-info/WHEEL
werkpool-0.2.0.dist-info/licenses/LICENSE
werkpool-0.2.0.dist-info/RECORD
