Metadata-Version: 2.4
Name: werkpool
Version: 0.2.0
Summary: Worker pool in Python with size and rate bounding options
License: MIT
License-File: LICENSE
Author: FlexDW
Author-email: 22373561+FlexDW@users.noreply.github.com
Requires-Python: >=3.12,<4.0
Classifier: License :: OSI Approved :: MIT License
Classifier: Programming Language :: Python :: 3
Classifier: Programming Language :: Python :: 3.12
Classifier: Programming Language :: Python :: 3.13
Classifier: Programming Language :: Python :: 3.14
Project-URL: Repository, https://github.com/FlexDW/py-workers
